AppcommPythonLogger/__init__.py
AppcommPythonLogger/main.py
Appcomm_python_Logger-2.5.dist-info/LICENSE
Appcomm_python_Logger-2.5.dist-info/METADATA
Appcomm_python_Logger-2.5.dist-info/WHEEL
Appcomm_python_Logger-2.5.dist-info/top_level.txt
Appcomm_python_Logger-2.5.dist-info/RECORD
