Metadata-Version: 2.2
Name: Appcomm_python_Logger
Version: 2.5
Summary: A python logger similair to the lavavel logs. Made for internal use in Appcomm.
Author-email: Furkan Öztürk <fu.ozturk25@gmail.com>
Classifier: Programming Language :: Python :: 3
Classifier: License :: OSI Approved :: MIT License
Classifier: Operating System :: OS Independent
Requires-Python: >=3.8
License-File: LICENSE
